postgis/geometrycollection.py
postgis/geojson.py
postgis/multipolygon.py
postgis/linestring.py
postgis/ewkb.c
postgis/ewkb.py
postgis/multipoint.py
postgis/asyncpg.py
postgis/psycopg.py
postgis/point.py
postgis/geometry.py
postgis/multilinestring.py
postgis/multi.py
postgis/__init__.py
postgis/polygon.py
postgis-1.0.4.dist-info/metadata.json
postgis-1.0.4.dist-info/METADATA
postgis-1.0.4.dist-info/RECORD
postgis-1.0.4.dist-info/WHEEL
postgis-1.0.4.dist-info/top_level.txt
postgis-1.0.4.dist-info/DESCRIPTION.rst
tests/psycopg/test_geometrycollection.py
tests/psycopg/test_point.py
tests/psycopg/test_linestring.py
tests/psycopg/conftest.py
tests/psycopg/test_multipoint.py
tests/psycopg/test_multipolygon.py
tests/psycopg/test_multilinestring.py
tests/psycopg/__init__.py
tests/psycopg/test_polygon.py
tests/asyncpg/test_geometrycollection.py
tests/asyncpg/test_point.py
tests/asyncpg/test_linestring.py
tests/asyncpg/conftest.py
tests/asyncpg/test_multipoint.py
tests/asyncpg/test_multipolygon.py
tests/asyncpg/test_multilinestring.py
tests/asyncpg/__init__.py
tests/asyncpg/test_polygon.py
