Metadata-Version: 1.1
Name: postgis
Version: 1.0.4
Summary: Pyscopg and asyncpg helpers to work with PostGIS.
Home-page: https://github.com/yohanboniface/python-postgis
Author: Yohan Boniface
Author-email: yohan.boniface@data.gouv.fr
License: WTFPL
Keywords: psycopg postgis gis asyncpg
Platform: UNKNOWN
Classifier: Development Status :: 4 - Beta
Classifier: Intended Audience :: Developers
Classifier: Topic :: Scientific/Engineering :: GIS
Classifier: Programming Language :: Python :: 3
Classifier: Programming Language :: Python :: 3.5
Classifier: Programming Language :: Python :: 3.6
